auth_utils/__init__.py
auth_utils/exceptions.py
auth_utils/middlewares.py
auth_utils/schemas.py
auth_utils_vpetrov-0.1.4.dist-info/METADATA
auth_utils_vpetrov-0.1.4.dist-info/WHEEL
auth_utils_vpetrov-0.1.4.dist-info/top_level.txt
auth_utils_vpetrov-0.1.4.dist-info/RECORD
