Metadata-Version: 2.1
Name: auth_utils_vpetrov
Version: 0.1.4
Requires-Dist: fastapi
Requires-Dist: pydantic
Requires-Dist: typing
Requires-Dist: user-utils-vpetrov
